icnews
